CaseInsensitiveDict/CaseInsensitiveDict.py
CaseInsensitiveDict/__init__.py
CaseInsensitiveDict-1.0.0.dist-info/DESCRIPTION.rst
CaseInsensitiveDict-1.0.0.dist-info/METADATA
CaseInsensitiveDict-1.0.0.dist-info/RECORD
CaseInsensitiveDict-1.0.0.dist-info/WHEEL
CaseInsensitiveDict-1.0.0.dist-info/metadata.json
CaseInsensitiveDict-1.0.0.dist-info/top_level.txt
