Metadata-Version: 2.0
Name: CaseInsensitiveDict
Version: 1.0.0
Summary: Case insensitive dictionary
Home-page: https://github.com/tivvit/python-case-insensitive-dict
Author: Vit Listik
Author-email: tivvit@seznam.cz
License: MIT
Keywords: dict dictionary case-insensitive
Platform: UNKNOWN
Classifier: Development Status :: 5 - Production/Stable
Classifier: Intended Audience :: Developers
Classifier: Topic :: Software Development :: Data structures
Classifier: License :: OSI Approved :: MIT License
Classifier: Programming Language :: Python :: 2
Classifier: Programming Language :: Python :: 2.6
Classifier: Programming Language :: Python :: 2.7
Classifier: Programming Language :: Python :: 3
Classifier: Programming Language :: Python :: 3.2
Classifier: Programming Language :: Python :: 3.3
Classifier: Programming Language :: Python :: 3.4
Classifier: Programming Language :: Python :: 3.5
Classifier: Programming Language :: Python :: pypy
